ganeshportfolio/__init__.py
ganeshportfolio-1.1.0.dist-info/LICENSE.txt
ganeshportfolio-1.1.0.dist-info/METADATA
ganeshportfolio-1.1.0.dist-info/WHEEL
ganeshportfolio-1.1.0.dist-info/top_level.txt
ganeshportfolio-1.1.0.dist-info/RECORD
