Metadata-Version: 2.1
Name: ganeshportfolio
Version: 1.1.0
Summary: Portfolio Package
Home-page: https://github.com/Ganeshuthiravasagam
Author: Ganesh Uthiravasagam
Author-email: ganeshuthiravasagam@gmail.com
License: UNKNOWN
Platform: UNKNOWN
Classifier: Programming Language :: Python :: 3
Classifier: License :: OSI Approved :: MIT License
Classifier: Operating System :: OS Independent
